JavaMianshiZhengliJavaZhuanlan/README.md
JavaMianshiZhengliJavaZhuanlan/__init__.py
JavaMianshiZhengliJavaZhuanlan/__main__.py
JavaMianshiZhengliJavaZhuanlan/file.epub
JavaMianshiZhengliJavaZhuanlan/index.html
JavaMianshiZhengliJavaZhuanlan/css/__init__.py
JavaMianshiZhengliJavaZhuanlan/css/annotations.css
JavaMianshiZhengliJavaZhuanlan/css/main.css
JavaMianshiZhengliJavaZhuanlan/css/normalize.css
JavaMianshiZhengliJavaZhuanlan/css/popup.css
JavaMianshiZhengliJavaZhuanlan/font/__init__.py
JavaMianshiZhengliJavaZhuanlan/font/fontello.eot
JavaMianshiZhengliJavaZhuanlan/font/fontello.svg
JavaMianshiZhengliJavaZhuanlan/font/fontello.ttf
JavaMianshiZhengliJavaZhuanlan/font/fontello.woff
JavaMianshiZhengliJavaZhuanlan/img/__init__.py
JavaMianshiZhengliJavaZhuanlan/img/annotator-glyph-sprite.png
JavaMianshiZhengliJavaZhuanlan/img/annotator-icon-sprite.png
JavaMianshiZhengliJavaZhuanlan/img/apple-touch-icon.png
JavaMianshiZhengliJavaZhuanlan/img/cancelfullscreen.png
JavaMianshiZhengliJavaZhuanlan/img/close.png
JavaMianshiZhengliJavaZhuanlan/img/fullscreen.png
JavaMianshiZhengliJavaZhuanlan/img/loader.gif
JavaMianshiZhengliJavaZhuanlan/img/menu-icon.png
JavaMianshiZhengliJavaZhuanlan/img/save.png
JavaMianshiZhengliJavaZhuanlan/img/saved.png
JavaMianshiZhengliJavaZhuanlan/img/settings-s.png
JavaMianshiZhengliJavaZhuanlan/img/settings.png
JavaMianshiZhengliJavaZhuanlan/img/star.png
JavaMianshiZhengliJavaZhuanlan/js/__init__.py
JavaMianshiZhengliJavaZhuanlan/js/epub.js
JavaMianshiZhengliJavaZhuanlan/js/epub.min.js
JavaMianshiZhengliJavaZhuanlan/js/epub.min.map
JavaMianshiZhengliJavaZhuanlan/js/hooks.min.js
JavaMianshiZhengliJavaZhuanlan/js/hooks.min.map
JavaMianshiZhengliJavaZhuanlan/js/reader.js
JavaMianshiZhengliJavaZhuanlan/js/reader.js.map
JavaMianshiZhengliJavaZhuanlan/js/reader.min.js
JavaMianshiZhengliJavaZhuanlan/js/reader.min.map
JavaMianshiZhengliJavaZhuanlan/js/hooks/__init__.py
JavaMianshiZhengliJavaZhuanlan/js/hooks/extensions/__init__.py
java_mianshi_zhengli_java_zhuanlan-2024.3.4.0.dist-info/METADATA
java_mianshi_zhengli_java_zhuanlan-2024.3.4.0.dist-info/WHEEL
java_mianshi_zhengli_java_zhuanlan-2024.3.4.0.dist-info/entry_points.txt
java_mianshi_zhengli_java_zhuanlan-2024.3.4.0.dist-info/top_level.txt
java_mianshi_zhengli_java_zhuanlan-2024.3.4.0.dist-info/RECORD
